<?xml version="1.0" encoding="iso-8859-1"?>
<items>
<playlist_name><![CDATA[CSI New.York T1 a T9]]></playlist_name>
 
<channel>
 <title><![CDATA[1x01]]></title>
<logo_30x30><![CDATA[]]></logo_30x30>
<description><![CDATA[<img src="http://hdfull.tv/tthumb/172x265/show_3efc8cc62864a33a3909f88efa50e937.jpg" />]]></description>                      
<stream_url><![CDATA[http://streamcloud.eu/c1aktvlhu78u]]></stream_url>
 </channel>
 
 <channel>
 <title><![CDATA[1x02]]></title>
<logo_30x30><![CDATA[]]></logo_30x30>
<description><![CDATA[<img src="http://hdfull.tv/tthumb/172x265/show_3efc8cc62864a33a3909f88efa50e937.jpg" />]]></description>                      
<stream_url><![CDATA[http://streamcloud.eu/l27mge0xgkk7]]></stream_url>
 </channel>
 
 <channel>
 <title><![CDATA[1x03]]></title>
<logo_30x30><![CDATA[]]></logo_30x30>
<description><![CDATA[<img src="http://hdfull.tv/tthumb/172x265/show_3efc8cc62864a33a3909f88efa50e937.jpg" />]]></description>                      
<stream_url><![CDATA[http://streamcloud.eu/2ov8fg8k1qly]]></stream_url>
 </channel>
 
 <channel>
 <title><![CDATA[1x04]]></title>
<logo_30x30><![CDATA[]]></logo_30x30>
<description><![CDATA[<img src="http://hdfull.tv/tthumb/172x265/show_3efc8cc62864a33a3909f88efa50e937.jpg" />]]></description>                      
<stream_url><![CDATA[http://streamcloud.eu/cs8kyscbq2pu]]></stream_url>
 </channel>
 
 <channel>
 <title><![CDATA[1x05]]></title>
<logo_30x30><![CDATA[]]></logo_30x30>
<description><![CDATA[<img src="http://hdfull.tv/tthumb/172x265/show_3efc8cc62864a33a3909f88efa50e937.jpg" />]]></description>                      
<stream_url><![CDATA[http://streamcloud.eu/o5o1yd20i22r]]></stream_url>
 </channel>
 
 <channel>
 <title><![CDATA[1x06]]></title>
<logo_30x30><![CDATA[]]></logo_30x30>
<description><![CDATA[<img src="http://hdfull.tv/tthumb/172x265/show_3efc8cc62864a33a3909f88efa50e937.jpg" />]]></description>                      
<stream_url><![CDATA[http://streamcloud.eu/crqdjb812a53]]></stream_url>
 </channel>
 
 <channel>
 <title><![CDATA[1x07]]></title>
<logo_30x30><![CDATA[]]></logo_30x30>
<description><![CDATA[<img src="http://hdfull.tv/tthumb/172x265/show_3efc8cc62864a33a3909f88efa50e937.jpg" />]]></description>                      
<stream_url><![CDATA[http://streamcloud.eu/zv39zqnuksnv]]></stream_url>
 </channel>
 
 <channel>
 <title><![CDATA[1x08]]></title>
<logo_30x30><![CDATA[]]></logo_30x30>
<description><![CDATA[<img src="http://hdfull.tv/tthumb/172x265/show_3efc8cc62864a33a3909f88efa50e937.jpg" />]]></description>                      
<stream_url><![CDATA[http://streamcloud.eu/7etqlcoxe9p1]]></stream_url>
 </channel>
 
 <channel>
 <title><![CDATA[1x09]]></title>
<logo_30x30><![CDATA[]]></logo_30x30>
<description><![CDATA[<img src="http://hdfull.tv/tthumb/172x265/show_3efc8cc62864a33a3909f88efa50e937.jpg" />]]></description>                      
<stream_url><![CDATA[http://streamcloud.eu/eqnw93paib8f]]></stream_url>
 </channel>
                           
<channel>
 <title><![CDATA[1x10]]></title>
<logo_30x30><![CDATA[]]></logo_30x30>
<description><![CDATA[<img src="http://hdfull.tv/tthumb/172x265/show_3efc8cc62864a33a3909f88efa50e937.jpg" />]]></description>                      
<stream_url><![CDATA[http://streamcloud.eu/minm9uea8bxc]]></stream_url>
 </channel>
 
<channel>
 <title><![CDATA[1x11]]></title>
<logo_30x30><![CDATA[]]></logo_30x30>
<description><![CDATA[<img src="http://hdfull.tv/tthumb/172x265/show_3efc8cc62864a33a3909f88efa50e937.jpg" />]]></description>                      
<stream_url><![CDATA[http://streamcloud.eu/rtdps7evdkah]]></stream_url>
 </channel>
 
<channel>
 <title><![CDATA[1x12]]></title>
<logo_30x30><![CDATA[]]></logo_30x30>
<description><![CDATA[<img src="http://hdfull.tv/tthumb/172x265/show_3efc8cc62864a33a3909f88efa50e937.jpg" />]]></description>                      
<stream_url><![CDATA[http://streamcloud.eu/np97wycrrxk4]]></stream_url>
 </channel>
 
<channel>
 <title><![CDATA[1x13]]></title>
<logo_30x30><![CDATA[]]></logo_30x30>
<description><![CDATA[<img src="http://hdfull.tv/tthumb/172x265/show_3efc8cc62864a33a3909f88efa50e937.jpg" />]]></description>                      
<stream_url><![CDATA[http://streamcloud.eu/g9ydsr5n5whd]]></stream_url>
 </channel>
 
<channel>
 <title><![CDATA[1x14]]></title>
<logo_30x30><![CDATA[]]></logo_30x30>
<description><![CDATA[<img src="http://hdfull.tv/tthumb/172x265/show_3efc8cc62864a33a3909f88efa50e937.jpg" />]]></description>                      
<stream_url><![CDATA[http://streamcloud.eu/433fmsfwhwyn]]></stream_url>
 </channel>
 
 <channel>
 <title><![CDATA[1x15]]></title>
<logo_30x30><![CDATA[]]></logo_30x30>
<description><![CDATA[<img src="http://hdfull.tv/tthumb/172x265/show_3efc8cc62864a33a3909f88efa50e937.jpg" />]]></description>                      
<stream_url><![CDATA[http://streamcloud.eu/8p5xl9ucf13w]]></stream_url>
 </channel>
 
 <channel>
 <title><![CDATA[1x16]]></title>
<logo_30x30><![CDATA[]]></logo_30x30>
<description><![CDATA[<img src="http://hdfull.tv/tthumb/172x265/show_3efc8cc62864a33a3909f88efa50e937.jpg" />]]></description>                      
<stream_url><![CDATA[http://streamcloud.eu/thtggtlblvcw]]></stream_url>
 </channel>
 
<channel>
 <title><![CDATA[1x17]]></title>
<logo_30x30><![CDATA[]]></logo_30x30>
<description><![CDATA[<img src="http://hdfull.tv/tthumb/172x265/show_3efc8cc62864a33a3909f88efa50e937.jpg" />]]></description>                      
<stream_url><![CDATA[https://archive.org/download/Csi.New.y0rk.Esp.1x17.avi/Csi.New.y0rk.Esp.1x17.avi.mp4]]></stream_url>
 </channel>
 
<channel>
 <title><![CDATA[1x18]]></title>
<logo_30x30><![CDATA[]]></logo_30x30>
<description><![CDATA[<img src="http://hdfull.tv/tthumb/172x265/show_3efc8cc62864a33a3909f88efa50e937.jpg" />]]></description>                      
<stream_url><![CDATA[http://streamcloud.eu/3r4dkcqm5mzv]]></stream_url>
 </channel>
 
 <channel>
 <title><![CDATA[1x19]]></title>
<logo_30x30><![CDATA[]]></logo_30x30>
<description><![CDATA[<img src="http://hdfull.tv/tthumb/172x265/show_3efc8cc62864a33a3909f88efa50e937.jpg" />]]></description>                      
<stream_url><![CDATA[http://streamcloud.eu/itb0zed9rhub]]></stream_url>
 </channel>
 
 <channel>
 <title><![CDATA[1x20]]></title>
<logo_30x30><![CDATA[]]></logo_30x30>
<description><![CDATA[<img src="http://hdfull.tv/tthumb/172x265/show_3efc8cc62864a33a3909f88efa50e937.jpg" />]]></description>                      
<stream_url><![CDATA[http://streamcloud.eu/gs99dhublkei]]></stream_url>
 </channel>
 
<channel>
 <title><![CDATA[1x21]]></title>
<logo_30x30><![CDATA[]]></logo_30x30>
<description><![CDATA[<img src="http://hdfull.tv/tthumb/172x265/show_3efc8cc62864a33a3909f88efa50e937.jpg" />]]></description>                      
<stream_url><![CDATA[http://streamcloud.eu/oq6tpp8qv09l]]></stream_url>
 </channel>
 
<channel>
 <title><![CDATA[1x22]]></title>
<logo_30x30><![CDATA[]]></logo_30x30>
<description><![CDATA[<img src="http://hdfull.tv/tthumb/172x265/show_3efc8cc62864a33a3909f88efa50e937.jpg" />]]></description>                      
<stream_url><![CDATA[http://streamcloud.eu/b7fndx45v0rh]]></stream_url>
 </channel>
 
 <channel>
 <title><![CDATA[1x23]]></title>
<logo_30x30><![CDATA[]]></logo_30x30>
<description><![CDATA[<img src="http://hdfull.tv/tthumb/172x265/show_3efc8cc62864a33a3909f88efa50e937.jpg" />]]></description>                      
<stream_url><![CDATA[http://streamcloud.eu/40ntz03sq719]]></stream_url>
 </channel>
 
 <channel>
 <title><![CDATA[2x01]]></title>
<logo_30x30><![CDATA[]]></logo_30x30>
<description><![CDATA[<img src="http://hdfull.tv/tthumb/172x265/show_3efc8cc62864a33a3909f88efa50e937.jpg" />]]></description>                      
<stream_url><![CDATA[http://streamcloud.eu/z4vxsg0jx93v]]></stream_url>
 </channel>
 
 <channel>
 <title><![CDATA[2x02]]></title>
<logo_30x30><![CDATA[]]></logo_30x30>
<description><![CDATA[<img src="http://hdfull.tv/tthumb/172x265/show_3efc8cc62864a33a3909f88efa50e937.jpg" />]]></description>                      
<stream_url><![CDATA[http://streamcloud.eu/xwpagbmbg0m5/CSl.NY.Es.0202.avi.html]]></stream_url>
 </channel>
 
 <channel>
 <title><![CDATA[2x03]]></title>
<logo_30x30><![CDATA[]]></logo_30x30>
<description><![CDATA[<img src="http://hdfull.tv/tthumb/172x265/show_3efc8cc62864a33a3909f88efa50e937.jpg" />]]></description>                      
<stream_url><![CDATA[http://streamcloud.eu/wodigfq6ce48]]></stream_url>
 </channel>
 
<channel>
 <title><![CDATA[2x04]]></title>
<logo_30x30><![CDATA[]]></logo_30x30>
<description><![CDATA[<img src="http://hdfull.tv/tthumb/172x265/show_3efc8cc62864a33a3909f88efa50e937.jpg" />]]></description>                      
<stream_url><![CDATA[http://streamcloud.eu/u72acy66br7x]]></stream_url>
 </channel>
 
 <channel>
 <title><![CDATA[2x05]]></title>
<logo_30x30><![CDATA[]]></logo_30x30>
<description><![CDATA[<img src="http://hdfull.tv/tthumb/172x265/show_3efc8cc62864a33a3909f88efa50e937.jpg" />]]></description>                      
<stream_url><![CDATA[http://streamcloud.eu/5xfn42pt2sk0]]></stream_url>
 </channel>
 
<channel>
 <title><![CDATA[2x06]]></title>
<logo_30x30><![CDATA[]]></logo_30x30>
<description><![CDATA[<img src="http://hdfull.tv/tthumb/172x265/show_3efc8cc62864a33a3909f88efa50e937.jpg" />]]></description>                      
<stream_url><![CDATA[http://streamcloud.eu/qjexewk0gb1b]]></stream_url>
 </channel>
 
 <channel>
 <title><![CDATA[2x07]]></title>
<logo_30x30><![CDATA[]]></logo_30x30>
<description><![CDATA[<img src="http://hdfull.tv/tthumb/172x265/show_3efc8cc62864a33a3909f88efa50e937.jpg" />]]></description>                      
<stream_url><![CDATA[http://streamcloud.eu/bwdkpcdfta6i]]></stream_url>
 </channel>
 
 <channel>
 <title><![CDATA[2x08]]></title>
<logo_30x30><![CDATA[]]></logo_30x30>
<description><![CDATA[<img src="http://hdfull.tv/tthumb/172x265/show_3efc8cc62864a33a3909f88efa50e937.jpg" />]]></description>                      
<stream_url><![CDATA[http://streamcloud.eu/av9hihvtuvj4]]></stream_url>
 </channel>
 
 <channel>
 <title><![CDATA[2x09]]></title>
<logo_30x30><![CDATA[]]></logo_30x30>
<description><![CDATA[<img src="http://hdfull.tv/tthumb/172x265/show_3efc8cc62864a33a3909f88efa50e937.jpg" />]]></description>                      
<stream_url><![CDATA[http://streamcloud.eu/4e2imhhmek0n]]></stream_url>
 </channel>
 
  <channel>
 <title><![CDATA[2x10]]></title>
<logo_30x30><![CDATA[]]></logo_30x30>
<description><![CDATA[<img src="http://hdfull.tv/tthumb/172x265/show_3efc8cc62864a33a3909f88efa50e937.jpg" />]]></description>                      
<stream_url><![CDATA[https://archive.org/download/Csi.New.y0rk.Esp.1x17.avi/Csi.New.y0rk.Esp.2x10.avi.mp4]]></stream_url>
 </channel>
   <channel>
 <title><![CDATA[2x11]]></title>
<logo_30x30><![CDATA[]]></logo_30x30>
<description><![CDATA[<img src="http://hdfull.tv/tthumb/172x265/show_3efc8cc62864a33a3909f88efa50e937.jpg" />]]></description>                      
<stream_url><![CDATA[http://streamcloud.eu/mkykhitek3ot/CSl.NY.Es.0211.avi.html]]></stream_url>
 </channel>
 
   <channel>
 <title><![CDATA[2x12]]></title>
<logo_30x30><![CDATA[]]></logo_30x30>
<description><![CDATA[<img src="http://hdfull.tv/tthumb/172x265/show_3efc8cc62864a33a3909f88efa50e937.jpg" />]]></description>                      
<stream_url><![CDATA[http://streamcloud.eu/zmd6uonvaj2i]]></stream_url>
 </channel>
 
   <channel>
 <title><![CDATA[2x13]]></title>
<logo_30x30><![CDATA[]]></logo_30x30>
<description><![CDATA[<img src="http://hdfull.tv/tthumb/172x265/show_3efc8cc62864a33a3909f88efa50e937.jpg" />]]></description>                      
<stream_url><![CDATA[http://streamcloud.eu/cp3f8j7ksso1]]></stream_url>
 </channel>
 
   <channel>
 <title><![CDATA[2x14]]></title>
<logo_30x30><![CDATA[]]></logo_30x30>
<description><![CDATA[<img src="http://hdfull.tv/tthumb/172x265/show_3efc8cc62864a33a3909f88efa50e937.jpg" />]]></description>                      
<stream_url><![CDATA[http://streamcloud.eu/rirtmu0j93hw]]></stream_url>
 </channel>
 
   <channel>
 <title><![CDATA[2x15]]></title>
<logo_30x30><![CDATA[]]></logo_30x30>
<description><![CDATA[<img src="http://hdfull.tv/tthumb/172x265/show_3efc8cc62864a33a3909f88efa50e937.jpg" />]]></description>                      
<stream_url><![CDATA[http://streamcloud.eu/war61yzjfi9w]]></stream_url>
 </channel>
 
   <channel>
 <title><![CDATA[2x16]]></title>
<logo_30x30><![CDATA[]]></logo_30x30>
<description><![CDATA[<img src="http://hdfull.tv/tthumb/172x265/show_3efc8cc62864a33a3909f88efa50e937.jpg" />]]></description>                      
<stream_url><![CDATA[http://streamcloud.eu/frbdl09qm42i]]></stream_url>
 </channel>
 
   <channel>
 <title><![CDATA[2x17]]></title>
<logo_30x30><![CDATA[]]></logo_30x30>
<description><![CDATA[<img src="http://hdfull.tv/tthumb/172x265/show_3efc8cc62864a33a3909f88efa50e937.jpg" />]]></description>                      
<stream_url><![CDATA[http://streamcloud.eu/at43cl5aq33d]]></stream_url>
 </channel>
 
   <channel>
 <title><![CDATA[2x18]]></title>
<logo_30x30><![CDATA[]]></logo_30x30>
<description><![CDATA[<img src="http://hdfull.tv/tthumb/172x265/show_3efc8cc62864a33a3909f88efa50e937.jpg" />]]></description>                      
<stream_url><![CDATA[http://streamcloud.eu/m32ookg8hzym/CSl.NY.Es.0218.avi.html]]></stream_url>
 </channel>
 
   <channel>
 <title><![CDATA[2x19]]></title>
<logo_30x30><![CDATA[]]></logo_30x30>
<description><![CDATA[<img src="http://hdfull.tv/tthumb/172x265/show_3efc8cc62864a33a3909f88efa50e937.jpg" />]]></description>                      
<stream_url><![CDATA[http://streamcloud.eu/bfiyri9h98z3]]></stream_url>
 </channel>
 
 <channel>
 <title><![CDATA[2x20]]></title>
<logo_30x30><![CDATA[]]></logo_30x30>
<description><![CDATA[<img src="http://hdfull.tv/tthumb/172x265/show_3efc8cc62864a33a3909f88efa50e937.jpg" />]]></description>                      
<stream_url><![CDATA[http://streamcloud.eu/6i7ftaxi6q7q]]></stream_url>
 </channel>
 
 <channel>
 <title><![CDATA[2x21]]></title>
<logo_30x30><![CDATA[]]></logo_30x30>
<description><![CDATA[<img src="http://hdfull.tv/tthumb/172x265/show_3efc8cc62864a33a3909f88efa50e937.jpg" />]]></description>                      
<stream_url><![CDATA[http://streamcloud.eu/d3g4jum4gkgr]]></stream_url>
 </channel>
 
 <channel>
 <title><![CDATA[2x22]]></title>
<logo_30x30><![CDATA[]]></logo_30x30>
<description><![CDATA[<img src="http://hdfull.tv/tthumb/172x265/show_3efc8cc62864a33a3909f88efa50e937.jpg" />]]></description>                      
<stream_url><![CDATA[http://streamcloud.eu/tjx0h23t6rnx]]></stream_url>
 </channel>
 
 <channel>
 <title><![CDATA[2x23]]></title>
<logo_30x30><![CDATA[]]></logo_30x30>
<description><![CDATA[<img src="http://hdfull.tv/tthumb/172x265/show_3efc8cc62864a33a3909f88efa50e937.jpg" />]]></description>                      
<stream_url><![CDATA[http://streamcloud.eu/dqoc8r3cixm7]]></stream_url>
 </channel>
 
 <channel>
 <title><![CDATA[2x24]]></title>
<logo_30x30><![CDATA[]]></logo_30x30>
<description><![CDATA[<img src="http://hdfull.tv/tthumb/172x265/show_3efc8cc62864a33a3909f88efa50e937.jpg" />]]></description>                      
<stream_url><![CDATA[http://streamcloud.eu/49i4vpc64t3f]]></stream_url>
 </channel>
 
  <channel>
 <title><![CDATA[3x01]]></title>
<logo_30x30><![CDATA[]]></logo_30x30>
<description><![CDATA[<img src="http://hdfull.tv/tthumb/172x265/show_3efc8cc62864a33a3909f88efa50e937.jpg" />]]></description>                      
<stream_url><![CDATA[http://streamcloud.eu/itnsrnj3ca2a]]></stream_url>
 </channel>
 
 <channel>
 <title><![CDATA[3x02]]></title>
<logo_30x30><![CDATA[]]></logo_30x30>
<description><![CDATA[<img src="http://hdfull.tv/tthumb/172x265/show_3efc8cc62864a33a3909f88efa50e937.jpg" />]]></description>                      
<stream_url><![CDATA[http://streamcloud.eu/qnwlkl77s1hg]]></stream_url>
 </channel>
 
 <channel>
 <title><![CDATA[3x03]]></title>
<logo_30x30><![CDATA[]]></logo_30x30>
<description><![CDATA[<img src="http://hdfull.tv/tthumb/172x265/show_3efc8cc62864a33a3909f88efa50e937.jpg" />]]></description>                      
<stream_url><![CDATA[http://streamcloud.eu/s4gqdskg58z8]]></stream_url>
 </channel>
 
 <channel>
 <title><![CDATA[3x04]]></title>
<logo_30x30><![CDATA[]]></logo_30x30>
<description><![CDATA[<img src="http://hdfull.tv/tthumb/172x265/show_3efc8cc62864a33a3909f88efa50e937.jpg" />]]></description>                      
<stream_url><![CDATA[http://streamcloud.eu/llr1pct4gklr]]></stream_url>
 </channel>
 
 <channel>
 <title><![CDATA[3x05]]></title>
<logo_30x30><![CDATA[]]></logo_30x30>
<description><![CDATA[<img src="http://hdfull.tv/tthumb/172x265/show_3efc8cc62864a33a3909f88efa50e937.jpg" />]]></description>                      
<stream_url><![CDATA[http://streamcloud.eu/986c93xjvd05]]></stream_url>
 </channel>
 
 <channel>
 <title><![CDATA[3x06]]></title>
<logo_30x30><![CDATA[]]></logo_30x30>
<description><![CDATA[<img src="http://hdfull.tv/tthumb/172x265/show_3efc8cc62864a33a3909f88efa50e937.jpg" />]]></description>                      
<stream_url><![CDATA[http://streamcloud.eu/4wfl8lm3yf1n]]></stream_url>
 </channel>
 
 <channel>
 <title><![CDATA[3x07]]></title>
<logo_30x30><![CDATA[]]></logo_30x30>
<description><![CDATA[<img src="http://hdfull.tv/tthumb/172x265/show_3efc8cc62864a33a3909f88efa50e937.jpg" />]]></description>                      
<stream_url><![CDATA[http://streamcloud.eu/9r2yh0pwdyu6/CSl.NY.Es.0307.avi.html]]></stream_url>
 </channel>
 
 <channel>
 <title><![CDATA[3x08]]></title>
<logo_30x30><![CDATA[]]></logo_30x30>
<description><![CDATA[<img src="http://hdfull.tv/tthumb/172x265/show_3efc8cc62864a33a3909f88efa50e937.jpg" />]]></description>                      
<stream_url><![CDATA[http://streamcloud.eu/etbq2dbqv2oi]]></stream_url>
 </channel>
 
 <channel>
 <title><![CDATA[3x09]]></title>
<logo_30x30><![CDATA[]]></logo_30x30>
<description><![CDATA[<img src="http://hdfull.tv/tthumb/172x265/show_3efc8cc62864a33a3909f88efa50e937.jpg" />]]></description>                      
<stream_url><![CDATA[http://streamcloud.eu/s7w7ylylg447]]></stream_url>
 </channel>
 
  <channel>
 <title><![CDATA[3x10]]></title>
<logo_30x30><![CDATA[]]></logo_30x30>
<description><![CDATA[<img src="http://hdfull.tv/tthumb/172x265/show_3efc8cc62864a33a3909f88efa50e937.jpg" />]]></description>                      
<stream_url><![CDATA[http://streamcloud.eu/t4524ib74y8m]]></stream_url>
 </channel>
 
  <channel>
 <title><![CDATA[3x11]]></title>
<logo_30x30><![CDATA[]]></logo_30x30>
<description><![CDATA[<img src="http://hdfull.tv/tthumb/172x265/show_3efc8cc62864a33a3909f88efa50e937.jpg" />]]></description>                      
<stream_url><![CDATA[http://streamcloud.eu/1ipuh4ymwwet]]></stream_url>
 </channel>
 
  <channel>
 <title><![CDATA[3x12]]></title>
<logo_30x30><![CDATA[]]></logo_30x30>
<description><![CDATA[<img src="http://hdfull.tv/tthumb/172x265/show_3efc8cc62864a33a3909f88efa50e937.jpg" />]]></description>                      
<stream_url><![CDATA[http://streamcloud.eu/2q1k818lsd5w]]></stream_url>
 </channel>
 
  <channel>
 <title><![CDATA[3x13]]></title>
<logo_30x30><![CDATA[]]></logo_30x30>
<description><![CDATA[<img src="http://hdfull.tv/tthumb/172x265/show_3efc8cc62864a33a3909f88efa50e937.jpg" />]]></description>                      
<stream_url><![CDATA[http://streamcloud.eu/o3ybcet390js]]></stream_url>
 </channel>
 
  <channel>
 <title><![CDATA[3x14]]></title>
<logo_30x30><![CDATA[]]></logo_30x30>
<description><![CDATA[<img src="http://hdfull.tv/tthumb/172x265/show_3efc8cc62864a33a3909f88efa50e937.jpg" />]]></description>                      
<stream_url><![CDATA[http://streamcloud.eu/l8qm99837xg2]]></stream_url>
 </channel>
 
  <channel>
 <title><![CDATA[3x15]]></title>
<logo_30x30><![CDATA[]]></logo_30x30>
<description><![CDATA[<img src="http://hdfull.tv/tthumb/172x265/show_3efc8cc62864a33a3909f88efa50e937.jpg" />]]></description>                      
<stream_url><![CDATA[http://streamcloud.eu/aw6xx4bgvsss]]></stream_url>
 </channel>
 
  <channel>
 <title><![CDATA[3x16]]></title>
<logo_30x30><![CDATA[]]></logo_30x30>
<description><![CDATA[<img src="http://hdfull.tv/tthumb/172x265/show_3efc8cc62864a33a3909f88efa50e937.jpg" />]]></description>                      
<stream_url><![CDATA[http://streamcloud.eu/pjv1a5wgw7kn]]></stream_url>
 </channel>
 
  <channel>
 <title><![CDATA[3x17]]></title>
<logo_30x30><![CDATA[]]></logo_30x30>
<description><![CDATA[<img src="http://hdfull.tv/tthumb/172x265/show_3efc8cc62864a33a3909f88efa50e937.jpg" />]]></description>                      
<stream_url><![CDATA[http://streamcloud.eu/0cbr9lg8yhs1]]></stream_url>
 </channel>
 
  <channel>
 <title><![CDATA[3x18]]></title>
<logo_30x30><![CDATA[]]></logo_30x30>
<description><![CDATA[<img src="http://hdfull.tv/tthumb/172x265/show_3efc8cc62864a33a3909f88efa50e937.jpg" />]]></description>                      
<stream_url><![CDATA[http://streamcloud.eu/phx61o4qsn8q]]></stream_url>
 </channel>
 
  <channel>
 <title><![CDATA[3x19]]></title>
<logo_30x30><![CDATA[]]></logo_30x30>
<description><![CDATA[<img src="http://hdfull.tv/tthumb/172x265/show_3efc8cc62864a33a3909f88efa50e937.jpg" />]]></description>                      
<stream_url><![CDATA[http://streamcloud.eu/holvgjw7woq7]]></stream_url>
 </channel>
 
  <channel>
 <title><![CDATA[3x20]]></title>
<logo_30x30><![CDATA[]]></logo_30x30>
<description><![CDATA[<img src="http://hdfull.tv/tthumb/172x265/show_3efc8cc62864a33a3909f88efa50e937.jpg" />]]></description>                      
<stream_url><![CDATA[http://streamcloud.eu/swaacaih3335]]></stream_url>
 </channel>
 
  <channel>
 <title><![CDATA[3x21]]></title>
<logo_30x30><![CDATA[]]></logo_30x30>
<description><![CDATA[<img src="http://hdfull.tv/tthumb/172x265/show_3efc8cc62864a33a3909f88efa50e937.jpg" />]]></description>                      
<stream_url><![CDATA[http://streamcloud.eu/qdg42ljp8jge]]></stream_url>
 </channel>
 
  <channel>
 <title><![CDATA[3x22]]></title>
<logo_30x30><![CDATA[]]></logo_30x30>
<description><![CDATA[<img src="http://hdfull.tv/tthumb/172x265/show_3efc8cc62864a33a3909f88efa50e937.jpg" />]]></description>                      
<stream_url><![CDATA[http://streamcloud.eu/n7pp148orgnh]]></stream_url>
 </channel>
 
  <channel>
 <title><![CDATA[3x23]]></title>
<logo_30x30><![CDATA[]]></logo_30x30>
<description><![CDATA[<img src="http://hdfull.tv/tthumb/172x265/show_3efc8cc62864a33a3909f88efa50e937.jpg" />]]></description>                      
<stream_url><![CDATA[http://streamcloud.eu/a0gihapl3til]]></stream_url>
 </channel>
 
  <channel>
 <title><![CDATA[3x24]]></title>
<logo_30x30><![CDATA[]]></logo_30x30>
<description><![CDATA[<img src="http://hdfull.tv/tthumb/172x265/show_3efc8cc62864a33a3909f88efa50e937.jpg" />]]></description>                      
<stream_url><![CDATA[http://streamcloud.eu/vnt19s44lflb]]></stream_url>
 </channel>
 
 <channel>
 <title><![CDATA[4x01]]></title>
<logo_30x30><![CDATA[]]></logo_30x30>
<description><![CDATA[<img src="http://hdfull.tv/tthumb/172x265/show_3efc8cc62864a33a3909f88efa50e937.jpg" />]]></description>                      
<stream_url><![CDATA[http://streamcloud.eu/21icmt4e5uzw]]></stream_url>
 </channel>
 
 <channel>
 <title><![CDATA[4x02]]></title>
<logo_30x30><![CDATA[]]></logo_30x30>
<description><![CDATA[<img src="http://hdfull.tv/tthumb/172x265/show_3efc8cc62864a33a3909f88efa50e937.jpg" />]]></description>                      
<stream_url><![CDATA[http://streamcloud.eu/3wj8935lnd4u]]></stream_url>
 </channel>
 
 <channel>
 <title><![CDATA[4x03]]></title>
<logo_30x30><![CDATA[]]></logo_30x30>
<description><![CDATA[<img src="http://hdfull.tv/tthumb/172x265/show_3efc8cc62864a33a3909f88efa50e937.jpg" />]]></description>                      
<stream_url><![CDATA[http://streamcloud.eu/okqgz359ttf9/CSl.NY.Es.0403.avi.html]]></stream_url>
 </channel>
 
 <channel>
 <title><![CDATA[4x04]]></title>
<logo_30x30><![CDATA[]]></logo_30x30>
<description><![CDATA[<img src="http://hdfull.tv/tthumb/172x265/show_3efc8cc62864a33a3909f88efa50e937.jpg" />]]></description>                      
<stream_url><![CDATA[http://streamcloud.eu/70zu4zov3816/CSl.NY.Es.0404.avi.html]]></stream_url>
 </channel>
 
 <channel>
 <title><![CDATA[4x05]]></title>
<logo_30x30><![CDATA[]]></logo_30x30>
<description><![CDATA[<img src="http://hdfull.tv/tthumb/172x265/show_3efc8cc62864a33a3909f88efa50e937.jpg" />]]></description>                      
<stream_url><![CDATA[http://streamcloud.eu/qmdztqgj55q2/CSl.NY.Es.0405.avi.html]]></stream_url>
 </channel>
 
 <channel>
 <title><![CDATA[4x06]]></title>
<logo_30x30><![CDATA[]]></logo_30x30>
<description><![CDATA[<img src="http://hdfull.tv/tthumb/172x265/show_3efc8cc62864a33a3909f88efa50e937.jpg" />]]></description>                      
<stream_url><![CDATA[http://streamcloud.eu/1uhtsx28lsux]]></stream_url>
 </channel>
 
 <channel>
 <title><![CDATA[4x07]]></title>
<logo_30x30><![CDATA[]]></logo_30x30>
<description><![CDATA[<img src="http://hdfull.tv/tthumb/172x265/show_3efc8cc62864a33a3909f88efa50e937.jpg" />]]></description>                      
<stream_url><![CDATA[http://streamcloud.eu/uolhd1uh9gfc]]></stream_url>
 </channel>
 
 <channel>
 <title><![CDATA[4x08]]></title>
<logo_30x30><![CDATA[]]></logo_30x30>
<description><![CDATA[<img src="http://hdfull.tv/tthumb/172x265/show_3efc8cc62864a33a3909f88efa50e937.jpg" />]]></description>                      
<stream_url><![CDATA[http://streamcloud.eu/l6h40fod7oyn]]></stream_url>
 </channel>
 
 <channel>
 <title><![CDATA[4x09]]></title>
<logo_30x30><![CDATA[]]></logo_30x30>
<description><![CDATA[<img src="http://hdfull.tv/tthumb/172x265/show_3efc8cc62864a33a3909f88efa50e937.jpg" />]]></description>                      
<stream_url><![CDATA[http://streamcloud.eu/005e17bm3otl]]></stream_url>
 </channel>
 
  <channel>
 <title><![CDATA[4x10]]></title>
<logo_30x30><![CDATA[]]></logo_30x30>
<description><![CDATA[<img src="http://hdfull.tv/tthumb/172x265/show_3efc8cc62864a33a3909f88efa50e937.jpg" />]]></description>                      
<stream_url><![CDATA[http://streamcloud.eu/0zllv4eo75ia]]></stream_url>
 </channel>
 
 <channel>
 <title><![CDATA[4x11]]></title>
<logo_30x30><![CDATA[]]></logo_30x30>
<description><![CDATA[<img src="http://hdfull.tv/tthumb/172x265/show_3efc8cc62864a33a3909f88efa50e937.jpg" />]]></description>                      
<stream_url><![CDATA[http://streamcloud.eu/tx83td0cld2h/CSl.NY.Es.0411.avi.html]]></stream_url>
 </channel>
 
 <channel>
 <title><![CDATA[4x12]]></title>
<logo_30x30><![CDATA[]]></logo_30x30>
<description><![CDATA[<img src="http://hdfull.tv/tthumb/172x265/show_3efc8cc62864a33a3909f88efa50e937.jpg" />]]></description>                      
<stream_url><![CDATA[http://streamcloud.eu/z128hsek07ll]]></stream_url>
 </channel>
 
 <channel>
 <title><![CDATA[4x13]]></title>
<logo_30x30><![CDATA[]]></logo_30x30>
<description><![CDATA[<img src="http://hdfull.tv/tthumb/172x265/show_3efc8cc62864a33a3909f88efa50e937.jpg" />]]></description>                      
<stream_url><![CDATA[http://streamcloud.eu/7x90yuede0dy/CSl.NY.Es.0413.avi.html]]></stream_url>
 </channel>
 
 <channel>
 <title><![CDATA[4x14]]></title>
<logo_30x30><![CDATA[]]></logo_30x30>
<description><![CDATA[<img src="http://hdfull.tv/tthumb/172x265/show_3efc8cc62864a33a3909f88efa50e937.jpg" />]]></description>                      
<stream_url><![CDATA[http://streamcloud.eu/yflmnewx28s4]]></stream_url>
 </channel>
 
 <channel>
 <title><![CDATA[4x15]]></title>
<logo_30x30><![CDATA[]]></logo_30x30>
<description><![CDATA[<img src="http://hdfull.tv/tthumb/172x265/show_3efc8cc62864a33a3909f88efa50e937.jpg" />]]></description>                      
<stream_url><![CDATA[http://streamcloud.eu/g6akhwtorpvc/CSl.NY.Es.0415.avi.html]]></stream_url>
 </channel>
 
 <channel>
 <title><![CDATA[4x16]]></title>
<logo_30x30><![CDATA[]]></logo_30x30>
<description><![CDATA[<img src="http://hdfull.tv/tthumb/172x265/show_3efc8cc62864a33a3909f88efa50e937.jpg" />]]></description>                      
<stream_url><![CDATA[http://streamcloud.eu/spln4g8xuzob/CSl.NY.Es.0416.avi.html]]></stream_url>
 </channel>
 
 <channel>
 <title><![CDATA[4x17]]></title>
<logo_30x30><![CDATA[]]></logo_30x30>
<description><![CDATA[<img src="http://hdfull.tv/tthumb/172x265/show_3efc8cc62864a33a3909f88efa50e937.jpg" />]]></description>                      
<stream_url><![CDATA[http://streamcloud.eu/2njxq5aydp2r/CSl.NY.Es.0417.avi.html]]></stream_url>
 </channel>
 
 <channel>
 <title><![CDATA[4x18]]></title>
<logo_30x30><![CDATA[]]></logo_30x30>
<description><![CDATA[<img src="http://hdfull.tv/tthumb/172x265/show_3efc8cc62864a33a3909f88efa50e937.jpg" />]]></description>                      
<stream_url><![CDATA[http://streamcloud.eu/59ash3kmql55]]></stream_url>
 </channel>
 
 <channel>
 <title><![CDATA[4x19]]></title>
<logo_30x30><![CDATA[]]></logo_30x30>
<description><![CDATA[<img src="http://hdfull.tv/tthumb/172x265/show_3efc8cc62864a33a3909f88efa50e937.jpg" />]]></description>                      
<stream_url><![CDATA[http://streamcloud.eu/i2yuveezwjxk]]></stream_url>
 </channel>
 
  <channel>
 <title><![CDATA[4x20]]></title>
<logo_30x30><![CDATA[]]></logo_30x30>
<description><![CDATA[<img src="http://hdfull.tv/tthumb/172x265/show_3efc8cc62864a33a3909f88efa50e937.jpg" />]]></description>                      
<stream_url><![CDATA[http://streamcloud.eu/a5xa4i98jxrh]]></stream_url>
 </channel>
 
  <channel>
 <title><![CDATA[4x21]]></title>
<logo_30x30><![CDATA[]]></logo_30x30>
<description><![CDATA[<img src="http://hdfull.tv/tthumb/172x265/show_3efc8cc62864a33a3909f88efa50e937.jpg" />]]></description>                      
<stream_url><![CDATA[http://streamcloud.eu/djdxbur0qfa0/CSl.NY.Es.0421.avi.html]]></stream_url>
 </channel>
 
  <channel>
 <title><![CDATA[5x01]]></title>
<logo_30x30><![CDATA[]]></logo_30x30>
<description><![CDATA[<img src="http://hdfull.tv/tthumb/172x265/show_3efc8cc62864a33a3909f88efa50e937.jpg" />]]></description>                      
<stream_url><![CDATA[http://streamcloud.eu/l2v21fbqxqbn]]></stream_url>
 </channel>
 
  <channel>
 <title><![CDATA[5x02]]></title>
<logo_30x30><![CDATA[]]></logo_30x30>
<description><![CDATA[<img src="http://hdfull.tv/tthumb/172x265/show_3efc8cc62864a33a3909f88efa50e937.jpg" />]]></description>                      
<stream_url><![CDATA[http://streamcloud.eu/jveuj5lpaubl]]></stream_url>
 </channel>

 
  <channel>
 <title><![CDATA[5x03]]></title>
<logo_30x30><![CDATA[]]></logo_30x30>
<description><![CDATA[<img src="http://hdfull.tv/tthumb/172x265/show_3efc8cc62864a33a3909f88efa50e937.jpg" />]]></description>                      
<stream_url><![CDATA[http://streamcloud.eu/4n2fv57o14ni]]></stream_url>
 </channel>

 
  <channel>
 <title><![CDATA[5x04]]></title>
<logo_30x30><![CDATA[]]></logo_30x30>
<description><![CDATA[<img src="http://hdfull.tv/tthumb/172x265/show_3efc8cc62864a33a3909f88efa50e937.jpg" />]]></description>                      
<stream_url><![CDATA[http://streamcloud.eu/zurc2pbqfh0z]]></stream_url>
 </channel>

 
  <channel>
 <title><![CDATA[5x05]]></title>
<logo_30x30><![CDATA[]]></logo_30x30>
<description><![CDATA[<img src="http://hdfull.tv/tthumb/172x265/show_3efc8cc62864a33a3909f88efa50e937.jpg" />]]></description>                      
<stream_url><![CDATA[http://streamcloud.eu/j95xe15sra3c]]></stream_url>
 </channel>

 
  <channel>
 <title><![CDATA[5x06]]></title>
<logo_30x30><![CDATA[]]></logo_30x30>
<description><![CDATA[<img src="http://hdfull.tv/tthumb/172x265/show_3efc8cc62864a33a3909f88efa50e937.jpg" />]]></description>                      
<stream_url><![CDATA[http://streamcloud.eu/vh63qwj0f29e]]></stream_url>
 </channel>

 
  <channel>
 <title><![CDATA[5x07]]></title>
<logo_30x30><![CDATA[]]></logo_30x30>
<description><![CDATA[<img src="http://hdfull.tv/tthumb/172x265/show_3efc8cc62864a33a3909f88efa50e937.jpg" />]]></description>                      
<stream_url><![CDATA[http://streamcloud.eu/mf9twzuwwfmc]]></stream_url>
 </channel>

 
  <channel>
 <title><![CDATA[5x08]]></title>
<logo_30x30><![CDATA[]]></logo_30x30>
<description><![CDATA[<img src="http://hdfull.tv/tthumb/172x265/show_3efc8cc62864a33a3909f88efa50e937.jpg" />]]></description>                      
<stream_url><![CDATA[http://streamcloud.eu/tvm64crogzh2/CSl.NY.Es.0508.avi.html]]></stream_url>
 </channel>

 
  <channel>
 <title><![CDATA[5x09]]></title>
<logo_30x30><![CDATA[]]></logo_30x30>
<description><![CDATA[<img src="http://hdfull.tv/tthumb/172x265/show_3efc8cc62864a33a3909f88efa50e937.jpg" />]]></description>                      
<stream_url><![CDATA[http://streamcloud.eu/clp9zx0327z5]]></stream_url>
 </channel>
 
   <channel>
 <title><![CDATA[5x10]]></title>
<logo_30x30><![CDATA[]]></logo_30x30>
<description><![CDATA[<img src="http://hdfull.tv/tthumb/172x265/show_3efc8cc62864a33a3909f88efa50e937.jpg" />]]></description>                      
<stream_url><![CDATA[http://streamcloud.eu/53f9fm3t5r6x]]></stream_url>
 </channel>
 
  <channel>
 <title><![CDATA[5x11]]></title>
<logo_30x30><![CDATA[]]></logo_30x30>
<description><![CDATA[<img src="http://hdfull.tv/tthumb/172x265/show_3efc8cc62864a33a3909f88efa50e937.jpg" />]]></description>                      
<stream_url><![CDATA[http://streamcloud.eu/a8erkzz7uvjs]]></stream_url>
 </channel>
 
  <channel>
 <title><![CDATA[5x12]]></title>
<logo_30x30><![CDATA[]]></logo_30x30>
<description><![CDATA[<img src="http://hdfull.tv/tthumb/172x265/show_3efc8cc62864a33a3909f88efa50e937.jpg" />]]></description>                      
<stream_url><![CDATA[http://streamcloud.eu/vybl8cplhytf/CSl.NY.Es.0512.avi.html]]></stream_url>
 </channel>
 
  <channel>
 <title><![CDATA[5x13]]></title>
<logo_30x30><![CDATA[]]></logo_30x30>
<description><![CDATA[<img src="http://hdfull.tv/tthumb/172x265/show_3efc8cc62864a33a3909f88efa50e937.jpg" />]]></description>                      
<stream_url><![CDATA[http://streamcloud.eu/gcnkz2qi54hm]]></stream_url>
 </channel>
 
  <channel>
 <title><![CDATA[5x14]]></title>
<logo_30x30><![CDATA[]]></logo_30x30>
<description><![CDATA[<img src="http://hdfull.tv/tthumb/172x265/show_3efc8cc62864a33a3909f88efa50e937.jpg" />]]></description>                      
<stream_url><![CDATA[http://streamcloud.eu/4o7br6nh7kqw]]></stream_url>
 </channel>
 
  <channel>
 <title><![CDATA[5x15]]></title>
<logo_30x30><![CDATA[]]></logo_30x30>
<description><![CDATA[<img src="http://hdfull.tv/tthumb/172x265/show_3efc8cc62864a33a3909f88efa50e937.jpg" />]]></description>                      
<stream_url><![CDATA[http://streamcloud.eu/edvnrr9f0jdq]]></stream_url>
 </channel>
 
  <channel>
 <title><![CDATA[5x16]]></title>
<logo_30x30><![CDATA[]]></logo_30x30>
<description><![CDATA[<img src="http://hdfull.tv/tthumb/172x265/show_3efc8cc62864a33a3909f88efa50e937.jpg" />]]></description>                      
<stream_url><![CDATA[http://streamcloud.eu/mbk29ydfjd1i]]></stream_url>
 </channel>
 
  <channel>
 <title><![CDATA[5x17]]></title>
<logo_30x30><![CDATA[]]></logo_30x30>
<description><![CDATA[<img src="http://hdfull.tv/tthumb/172x265/show_3efc8cc62864a33a3909f88efa50e937.jpg" />]]></description>                      
<stream_url><![CDATA[http://streamcloud.eu/5zy61v52yxuz]]></stream_url>
 </channel>
 
  <channel>
 <title><![CDATA[5x18]]></title>
<logo_30x30><![CDATA[]]></logo_30x30>
<description><![CDATA[<img src="http://hdfull.tv/tthumb/172x265/show_3efc8cc62864a33a3909f88efa50e937.jpg" />]]></description>                      
<stream_url><![CDATA[http://streamcloud.eu/ipwpl5ujo9k0]]></stream_url>
 </channel>
 
  <channel>
 <title><![CDATA[5x19]]></title>
<logo_30x30><![CDATA[]]></logo_30x30>
<description><![CDATA[<img src="http://hdfull.tv/tthumb/172x265/show_3efc8cc62864a33a3909f88efa50e937.jpg" />]]></description>                      
<stream_url><![CDATA[http://streamcloud.eu/oy5pi5vzz5y2]]></stream_url>
 </channel>
 
   <channel>
 <title><![CDATA[5x20]]></title>
<logo_30x30><![CDATA[]]></logo_30x30>
<description><![CDATA[<img src="http://hdfull.tv/tthumb/172x265/show_3efc8cc62864a33a3909f88efa50e937.jpg" />]]></description>                      
<stream_url><![CDATA[http://streamcloud.eu/nzhossuu49rx/CSl.NY.Es.0520.avi.html]]></stream_url>
 </channel>
 
  <channel>
 <title><![CDATA[5x21]]></title>
<logo_30x30><![CDATA[]]></logo_30x30>
<description><![CDATA[<img src="http://hdfull.tv/tthumb/172x265/show_3efc8cc62864a33a3909f88efa50e937.jpg" />]]></description>                      
<stream_url><![CDATA[http://streamcloud.eu/49ia55vnu2o2]]></stream_url>
 </channel>
 
  <channel>
 <title><![CDATA[5x22]]></title>
<logo_30x30><![CDATA[]]></logo_30x30>
<description><![CDATA[<img src="http://hdfull.tv/tthumb/172x265/show_3efc8cc62864a33a3909f88efa50e937.jpg" />]]></description>                      
<stream_url><![CDATA[http://streamcloud.eu/7o0ittrgka2e/CSl.NY.Es.0522.avi.html]]></stream_url>
 </channel>
 
  <channel>
 <title><![CDATA[5x23]]></title>
<logo_30x30><![CDATA[]]></logo_30x30>
<description><![CDATA[<img src="http://hdfull.tv/tthumb/172x265/show_3efc8cc62864a33a3909f88efa50e937.jpg" />]]></description>                      
<stream_url><![CDATA[http://streamcloud.eu/boyl73hmqu26/CSl.NY.Es.0523.avi.html]]></stream_url>
 </channel>
 
  <channel>
 <title><![CDATA[5x24]]></title>
<logo_30x30><![CDATA[]]></logo_30x30>
<description><![CDATA[<img src="http://hdfull.tv/tthumb/172x265/show_3efc8cc62864a33a3909f88efa50e937.jpg" />]]></description>                      
<stream_url><![CDATA[http://streamcloud.eu/mzgut56m5t3b]]></stream_url>
 </channel>
 
  <channel>
 <title><![CDATA[5x25]]></title>
<logo_30x30><![CDATA[]]></logo_30x30>
<description><![CDATA[<img src="http://hdfull.tv/tthumb/172x265/show_3efc8cc62864a33a3909f88efa50e937.jpg" />]]></description>                      
<stream_url><![CDATA[http://streamcloud.eu/wlxqqayuinl3/CSl.NY.Es.0525.avi.html]]></stream_url>
 </channel>
 
  <channel>
 <title><![CDATA[6x01]]></title>
<logo_30x30><![CDATA[]]></logo_30x30>
<description><![CDATA[<img src="http://hdfull.tv/tthumb/172x265/show_3efc8cc62864a33a3909f88efa50e937.jpg" />]]></description>                      
<stream_url><![CDATA[http://streamcloud.eu/w5zm1yz44ytz/CSI_Nueva_York_S06E01_Cast.avi.html]]></stream_url>
 </channel>
 
  <channel>
 <title><![CDATA[6x02]]></title>
<logo_30x30><![CDATA[]]></logo_30x30>
<description><![CDATA[<img src="http://hdfull.tv/tthumb/172x265/show_3efc8cc62864a33a3909f88efa50e937.jpg" />]]></description>                      
<stream_url><![CDATA[http://streamcloud.eu/bcslo04cdpd6/CSl.NY.Es.0602.avi.html]]></stream_url>
 </channel>
 
  <channel>
 <title><![CDATA[6x03]]></title>
<logo_30x30><![CDATA[]]></logo_30x30>
<description><![CDATA[<img src="http://hdfull.tv/tthumb/172x265/show_3efc8cc62864a33a3909f88efa50e937.jpg" />]]></description>                      
<stream_url><![CDATA[http://streamcloud.eu/jn2llgm7uh04/CSl.NY.Es.0603.avi.html]]></stream_url>
 </channel>
 
  <channel>
 <title><![CDATA[6x04]]></title>
<logo_30x30><![CDATA[]]></logo_30x30>
<description><![CDATA[<img src="http://hdfull.tv/tthumb/172x265/show_3efc8cc62864a33a3909f88efa50e937.jpg" />]]></description>                      
<stream_url><![CDATA[http://streamcloud.eu/u6rd3g9h95b6]]></stream_url>
 </channel>
 
  <channel>
 <title><![CDATA[6x05]]></title>
<logo_30x30><![CDATA[]]></logo_30x30>
<description><![CDATA[<img src="http://hdfull.tv/tthumb/172x265/show_3efc8cc62864a33a3909f88efa50e937.jpg" />]]></description>                      
<stream_url><![CDATA[http://streamcloud.eu/ak2kjf6mlve7]]></stream_url>
 </channel>
 
  <channel>
 <title><![CDATA[6x06]]></title>
<logo_30x30><![CDATA[]]></logo_30x30>
<description><![CDATA[<img src="http://hdfull.tv/tthumb/172x265/show_3efc8cc62864a33a3909f88efa50e937.jpg" />]]></description>                      
<stream_url><![CDATA[http://streamcloud.eu/h22d3pypgxu2/CSl.NY.Es.0606.avi.html]]></stream_url>
 </channel>
 
  <channel>
 <title><![CDATA[6x07]]></title>
<logo_30x30><![CDATA[]]></logo_30x30>
<description><![CDATA[<img src="http://hdfull.tv/tthumb/172x265/show_3efc8cc62864a33a3909f88efa50e937.jpg" />]]></description>                      
<stream_url><![CDATA[http://streamcloud.eu/pthehuv2rt34/CSl.NY.Es.0607.avi.html]]></stream_url>
 </channel>
 
  <channel>
 <title><![CDATA[6x08]]></title>
<logo_30x30><![CDATA[]]></logo_30x30>
<description><![CDATA[<img src="http://hdfull.tv/tthumb/172x265/show_3efc8cc62864a33a3909f88efa50e937.jpg" />]]></description>                      
<stream_url><![CDATA[http://streamcloud.eu/9qzvp5t7wtjl/CSl.NY.Es.0608.avi.html]]></stream_url>
 </channel>
 
  <channel>
 <title><![CDATA[6x09]]></title>
<logo_30x30><![CDATA[]]></logo_30x30>
<description><![CDATA[<img src="http://hdfull.tv/tthumb/172x265/show_3efc8cc62864a33a3909f88efa50e937.jpg" />]]></description>                      
<stream_url><![CDATA[http://streamcloud.eu/dn3gkjn949qb]]></stream_url>
 </channel>
 
  <channel>
 <title><![CDATA[6x10]]></title>
<logo_30x30><![CDATA[]]></logo_30x30>
<description><![CDATA[<img src="http://hdfull.tv/tthumb/172x265/show_3efc8cc62864a33a3909f88efa50e937.jpg" />]]></description>                      
<stream_url><![CDATA[http://streamcloud.eu/vjpw0p76gmhu]]></stream_url>
 </channel>
 
  <channel>
 <title><![CDATA[6x11]]></title>
<logo_30x30><![CDATA[]]></logo_30x30>
<description><![CDATA[<img src="http://hdfull.tv/tthumb/172x265/show_3efc8cc62864a33a3909f88efa50e937.jpg" />]]></description>                      
<stream_url><![CDATA[http://streamcloud.eu/tmm768ukvvx1]]></stream_url>
 </channel>
 
  <channel>
 <title><![CDATA[6x12]]></title>
<logo_30x30><![CDATA[]]></logo_30x30>
<description><![CDATA[<img src="http://hdfull.tv/tthumb/172x265/show_3efc8cc62864a33a3909f88efa50e937.jpg" />]]></description>                      
<stream_url><![CDATA[http://streamcloud.eu/9ir8s6d23qzz/CSl.NY.Es.0612.avi.html]]></stream_url>
 </channel>
 
  <channel>
 <title><![CDATA[6x13]]></title>
<logo_30x30><![CDATA[]]></logo_30x30>
<description><![CDATA[<img src="http://hdfull.tv/tthumb/172x265/show_3efc8cc62864a33a3909f88efa50e937.jpg" />]]></description>                      
<stream_url><![CDATA[http://streamcloud.eu/v1dyuixdm8fi]]></stream_url>
 </channel>
 
  <channel>
 <title><![CDATA[6x14]]></title>
<logo_30x30><![CDATA[]]></logo_30x30>
<description><![CDATA[<img src="http://hdfull.tv/tthumb/172x265/show_3efc8cc62864a33a3909f88efa50e937.jpg" />]]></description>                      
<stream_url><![CDATA[http://streamcloud.eu/ll9eichvk47q]]></stream_url>
 </channel>
 
  <channel>
 <title><![CDATA[6x15]]></title>
<logo_30x30><![CDATA[]]></logo_30x30>
<description><![CDATA[<img src="http://hdfull.tv/tthumb/172x265/show_3efc8cc62864a33a3909f88efa50e937.jpg" />]]></description>                      
<stream_url><![CDATA[http://streamcloud.eu/lc0uma0nv6n9/CSl.NY.Es.0615.avi.html]]></stream_url>
 </channel>
 
  <channel>
 <title><![CDATA[6x16]]></title>
<logo_30x30><![CDATA[]]></logo_30x30>
<description><![CDATA[<img src="http://hdfull.tv/tthumb/172x265/show_3efc8cc62864a33a3909f88efa50e937.jpg" />]]></description>                      
<stream_url><![CDATA[http://streamcloud.eu/53pii2as9id7]]></stream_url>
 </channel>
 
  <channel>
 <title><![CDATA[6x17]]></title>
<logo_30x30><![CDATA[]]></logo_30x30>
<description><![CDATA[<img src="http://hdfull.tv/tthumb/172x265/show_3efc8cc62864a33a3909f88efa50e937.jpg" />]]></description>                      
<stream_url><![CDATA[http://streamcloud.eu/q8rre9v680dz]]></stream_url>
 </channel>
 
  <channel>
 <title><![CDATA[6x18]]></title>
<logo_30x30><![CDATA[]]></logo_30x30>
<description><![CDATA[<img src="http://hdfull.tv/tthumb/172x265/show_3efc8cc62864a33a3909f88efa50e937.jpg" />]]></description>                      
<stream_url><![CDATA[http://streamcloud.eu/g42djohcd0hj]]></stream_url>
 </channel>
 
  <channel>
 <title><![CDATA[6x19]]></title>
<logo_30x30><![CDATA[]]></logo_30x30>
<description><![CDATA[<img src="http://hdfull.tv/tthumb/172x265/show_3efc8cc62864a33a3909f88efa50e937.jpg" />]]></description>                      
<stream_url><![CDATA[http://streamcloud.eu/xe3ruk3i3gtq/CSl.NY.Es.0619.avi.html]]></stream_url>
 </channel>
 
  <channel>
 <title><![CDATA[6x20]]></title>
<logo_30x30><![CDATA[]]></logo_30x30>
<description><![CDATA[<img src="http://hdfull.tv/tthumb/172x265/show_3efc8cc62864a33a3909f88efa50e937.jpg" />]]></description>                      
<stream_url><![CDATA[http://streamcloud.eu/m05o7w2zlw3p/CSl.NY.Es.0620.avi.html]]></stream_url>
 </channel>
 
 <channel>
 <title><![CDATA[6x21]]></title>
<logo_30x30><![CDATA[]]></logo_30x30>
<description><![CDATA[<img src="http://hdfull.tv/tthumb/172x265/show_3efc8cc62864a33a3909f88efa50e937.jpg" />]]></description>                      
<stream_url><![CDATA[http://streamcloud.eu/em15h9f8igul]]></stream_url>
 </channel>
 
 <channel>
 <title><![CDATA[6x22]]></title>
<logo_30x30><![CDATA[]]></logo_30x30>
<description><![CDATA[<img src="http://hdfull.tv/tthumb/172x265/show_3efc8cc62864a33a3909f88efa50e937.jpg" />]]></description>                      
<stream_url><![CDATA[http://streamcloud.eu/o7zx62mhwg53/CSl.NY.Es.0622.avi.html]]></stream_url>
 </channel>
 
 <channel>
 <title><![CDATA[6x23]]></title>
<logo_30x30><![CDATA[]]></logo_30x30>
<description><![CDATA[<img src="http://hdfull.tv/tthumb/172x265/show_3efc8cc62864a33a3909f88efa50e937.jpg" />]]></description>                      
<stream_url><![CDATA[http://streamcloud.eu/ip4c616odu3z]]></stream_url>
 </channel>
 
  <channel>
 <title><![CDATA[7x01]]></title>
<logo_30x30><![CDATA[]]></logo_30x30>
<description><![CDATA[<img src="http://hdfull.tv/tthumb/172x265/show_3efc8cc62864a33a3909f88efa50e937.jpg" />]]></description>                      
<stream_url><![CDATA[http://streamcloud.eu/jlh4hr22uw71]]></stream_url>
 </channel>
 
 <channel>
 <title><![CDATA[7x02]]></title>
<logo_30x30><![CDATA[]]></logo_30x30>
<description><![CDATA[<img src="http://hdfull.tv/tthumb/172x265/show_3efc8cc62864a33a3909f88efa50e937.jpg" />]]></description>                      
<stream_url><![CDATA[http://streamcloud.eu/risc3l14iofs]]></stream_url>
 </channel>
 
 <channel>
 <title><![CDATA[7x03]]></title>
<logo_30x30><![CDATA[]]></logo_30x30>
<description><![CDATA[<img src="http://hdfull.tv/tthumb/172x265/show_3efc8cc62864a33a3909f88efa50e937.jpg" />]]></description>                      
<stream_url><![CDATA[http://streamcloud.eu/itznwh4050ph]]></stream_url>
 </channel>
 
 <channel>
 <title><![CDATA[7x04]]></title>
<logo_30x30><![CDATA[]]></logo_30x30>
<description><![CDATA[<img src="http://hdfull.tv/tthumb/172x265/show_3efc8cc62864a33a3909f88efa50e937.jpg" />]]></description>                      
<stream_url><![CDATA[http://streamcloud.eu/843ny5xyarl5]]></stream_url>
 </channel>
 
 <channel>
 <title><![CDATA[7x05]]></title>
<logo_30x30><![CDATA[]]></logo_30x30>
<description><![CDATA[<img src="http://hdfull.tv/tthumb/172x265/show_3efc8cc62864a33a3909f88efa50e937.jpg" />]]></description>                      
<stream_url><![CDATA[http://streamcloud.eu/dm7jo8crrx3d]]></stream_url>
 </channel>
 
 <channel>
 <title><![CDATA[7x06]]></title>
<logo_30x30><![CDATA[]]></logo_30x30>
<description><![CDATA[<img src="http://hdfull.tv/tthumb/172x265/show_3efc8cc62864a33a3909f88efa50e937.jpg" />]]></description>                      
<stream_url><![CDATA[http://streamcloud.eu/xax5pdb129ka]]></stream_url>
 </channel>
 
 <channel>
 <title><![CDATA[7x07]]></title>
<logo_30x30><![CDATA[]]></logo_30x30>
<description><![CDATA[<img src="http://hdfull.tv/tthumb/172x265/show_3efc8cc62864a33a3909f88efa50e937.jpg" />]]></description>                      
<stream_url><![CDATA[http://streamcloud.eu/ikqlooke2937]]></stream_url>
 </channel>
 
 <channel>
 <title><![CDATA[7x08]]></title>
<logo_30x30><![CDATA[]]></logo_30x30>
<description><![CDATA[<img src="http://hdfull.tv/tthumb/172x265/show_3efc8cc62864a33a3909f88efa50e937.jpg" />]]></description>                      
<stream_url><![CDATA[http://streamcloud.eu/fxi7ho3kb8mg]]></stream_url>
 </channel>
 
 <channel>
 <title><![CDATA[7x09]]></title>
<logo_30x30><![CDATA[]]></logo_30x30>
<description><![CDATA[<img src="http://hdfull.tv/tthumb/172x265/show_3efc8cc62864a33a3909f88efa50e937.jpg" />]]></description>                      
<stream_url><![CDATA[http://streamcloud.eu/4iril8itojir]]></stream_url>
 </channel>
 
  <channel>
 <title><![CDATA[7x10]]></title>
<logo_30x30><![CDATA[]]></logo_30x30>
<description><![CDATA[<img src="http://hdfull.tv/tthumb/172x265/show_3efc8cc62864a33a3909f88efa50e937.jpg" />]]></description>                      
<stream_url><![CDATA[http://streamcloud.eu/27veb0kg2x1i]]></stream_url>
 </channel>
 
 <channel>
 <title><![CDATA[7x11]]></title>
<logo_30x30><![CDATA[]]></logo_30x30>
<description><![CDATA[<img src="http://hdfull.tv/tthumb/172x265/show_3efc8cc62864a33a3909f88efa50e937.jpg" />]]></description>                      
<stream_url><![CDATA[http://streamcloud.eu/cx2w3i8nls3y]]></stream_url>
 </channel>
 
 <channel>
 <title><![CDATA[7x12]]></title>
<logo_30x30><![CDATA[]]></logo_30x30>
<description><![CDATA[<img src="http://hdfull.tv/tthumb/172x265/show_3efc8cc62864a33a3909f88efa50e937.jpg" />]]></description>                      
<stream_url><![CDATA[http://streamcloud.eu/vypqr0wt3vik]]></stream_url>
 </channel>
 
 <channel>
 <title><![CDATA[7x13]]></title>
<logo_30x30><![CDATA[]]></logo_30x30>
<description><![CDATA[<img src="http://hdfull.tv/tthumb/172x265/show_3efc8cc62864a33a3909f88efa50e937.jpg" />]]></description>                      
<stream_url><![CDATA[http://streamcloud.eu/vabmit2vy75d]]></stream_url>
 </channel>
 
 <channel>
 <title><![CDATA[7x14]]></title>
<logo_30x30><![CDATA[]]></logo_30x30>
<description><![CDATA[<img src="http://hdfull.tv/tthumb/172x265/show_3efc8cc62864a33a3909f88efa50e937.jpg" />]]></description>                      
<stream_url><![CDATA[http://streamcloud.eu/k12pdcl4268k]]></stream_url>
 </channel>
 
 <channel>
 <title><![CDATA[7x15]]></title>
<logo_30x30><![CDATA[]]></logo_30x30>
<description><![CDATA[<img src="http://hdfull.tv/tthumb/172x265/show_3efc8cc62864a33a3909f88efa50e937.jpg" />]]></description>                      
<stream_url><![CDATA[http://streamcloud.eu/e76bo41xyfvh]]></stream_url>
 </channel>
 
 <channel>
 <title><![CDATA[7x16]]></title>
<logo_30x30><![CDATA[]]></logo_30x30>
<description><![CDATA[<img src="http://hdfull.tv/tthumb/172x265/show_3efc8cc62864a33a3909f88efa50e937.jpg" />]]></description>                      
<stream_url><![CDATA[http://streamcloud.eu/o5nmhy20kt64]]></stream_url>
 </channel>
 
 <channel>
 <title><![CDATA[7x17]]></title>
<logo_30x30><![CDATA[]]></logo_30x30>
<description><![CDATA[<img src="http://hdfull.tv/tthumb/172x265/show_3efc8cc62864a33a3909f88efa50e937.jpg" />]]></description>                      
<stream_url><![CDATA[http://streamcloud.eu/7f3lkocsddqp]]></stream_url>
 </channel>
 
 <channel>
 <title><![CDATA[7x18]]></title>
<logo_30x30><![CDATA[]]></logo_30x30>
<description><![CDATA[<img src="http://hdfull.tv/tthumb/172x265/show_3efc8cc62864a33a3909f88efa50e937.jpg" />]]></description>                      
<stream_url><![CDATA[http://streamcloud.eu/27veb0kg2x1i]]></stream_url>
 </channel>
 
 <channel>
 <title><![CDATA[7x19]]></title>
<logo_30x30><![CDATA[]]></logo_30x30>
<description><![CDATA[<img src="http://hdfull.tv/tthumb/172x265/show_3efc8cc62864a33a3909f88efa50e937.jpg" />]]></description>                      
<stream_url><![CDATA[http://streamcloud.eu/grom0c19yq29]]></stream_url>
 </channel>
 
  <channel>
 <title><![CDATA[7x20]]></title>
<logo_30x30><![CDATA[]]></logo_30x30>
<description><![CDATA[<img src="http://hdfull.tv/tthumb/172x265/show_3efc8cc62864a33a3909f88efa50e937.jpg" />]]></description>                      
<stream_url><![CDATA[http://streamcloud.eu/rp3mldjhmj05]]></stream_url>
 </channel>
 
  <channel>
 <title><![CDATA[7x21]]></title>
<logo_30x30><![CDATA[]]></logo_30x30>
<description><![CDATA[<img src="http://hdfull.tv/tthumb/172x265/show_3efc8cc62864a33a3909f88efa50e937.jpg" />]]></description>                      
<stream_url><![CDATA[http://streamcloud.eu/3lpnwwdpfhfp]]></stream_url>
 </channel>
 
  <channel>
 <title><![CDATA[7x22]]></title>
<logo_30x30><![CDATA[]]></logo_30x30>
<description><![CDATA[<img src="http://hdfull.tv/tthumb/172x265/show_3efc8cc62864a33a3909f88efa50e937.jpg" />]]></description>                      
<stream_url><![CDATA[http://streamcloud.eu/mbibvuv3gneo]]></stream_url>
 </channel>
 
  <channel>
 <title><![CDATA[8x01]]></title>
<logo_30x30><![CDATA[]]></logo_30x30>
<description><![CDATA[<img src="http://hdfull.tv/tthumb/172x265/show_3efc8cc62864a33a3909f88efa50e937.jpg" />]]></description>                      
<stream_url><![CDATA[http://streamcloud.eu/hdk6trv4ed1h]]></stream_url>
 </channel>
 
  <channel>
 <title><![CDATA[8x02]]></title>
<logo_30x30><![CDATA[]]></logo_30x30>
<description><![CDATA[<img src="http://hdfull.tv/tthumb/172x265/show_3efc8cc62864a33a3909f88efa50e937.jpg" />]]></description>                      
<stream_url><![CDATA[http://streamcloud.eu/bei275bk75jw]]></stream_url>
 </channel>
 
  <channel>
 <title><![CDATA[8x03]]></title>
<logo_30x30><![CDATA[]]></logo_30x30>
<description><![CDATA[<img src="http://hdfull.tv/tthumb/172x265/show_3efc8cc62864a33a3909f88efa50e937.jpg" />]]></description>                      
<stream_url><![CDATA[http://streamcloud.eu/pn51ua70w00j]]></stream_url>
 </channel>
 
  <channel>
 <title><![CDATA[8x04]]></title>
<logo_30x30><![CDATA[]]></logo_30x30>
<description><![CDATA[<img src="http://hdfull.tv/tthumb/172x265/show_3efc8cc62864a33a3909f88efa50e937.jpg" />]]></description>                      
<stream_url><![CDATA[http://streamcloud.eu/avwo8jqp9tdl]]></stream_url>
 </channel>
 
  <channel>
 <title><![CDATA[8x05]]></title>
<logo_30x30><![CDATA[]]></logo_30x30>
<description><![CDATA[<img src="http://hdfull.tv/tthumb/172x265/show_3efc8cc62864a33a3909f88efa50e937.jpg" />]]></description>                      
<stream_url><![CDATA[http://streamcloud.eu/xzepmstony1h]]></stream_url>
 </channel>
 
  <channel>
 <title><![CDATA[8x06]]></title>
<logo_30x30><![CDATA[]]></logo_30x30>
<description><![CDATA[<img src="http://hdfull.tv/tthumb/172x265/show_3efc8cc62864a33a3909f88efa50e937.jpg" />]]></description>                      
<stream_url><![CDATA[http://streamcloud.eu/o0eqypp5c2an]]></stream_url>
 </channel>
 
  <channel>
 <title><![CDATA[8x07]]></title>
<logo_30x30><![CDATA[]]></logo_30x30>
<description><![CDATA[<img src="http://hdfull.tv/tthumb/172x265/show_3efc8cc62864a33a3909f88efa50e937.jpg" />]]></description>                      
<stream_url><![CDATA[http://streamcloud.eu/1dk0vm0scowq]]></stream_url>
 </channel>
 
  <channel>
 <title><![CDATA[8x08]]></title>
<logo_30x30><![CDATA[]]></logo_30x30>
<description><![CDATA[<img src="http://hdfull.tv/tthumb/172x265/show_3efc8cc62864a33a3909f88efa50e937.jpg" />]]></description>                      
<stream_url><![CDATA[http://streamcloud.eu/x66a893s61kt]]></stream_url>
 </channel>
 
  <channel>
 <title><![CDATA[8x09]]></title>
<logo_30x30><![CDATA[]]></logo_30x30>
<description><![CDATA[<img src="http://hdfull.tv/tthumb/172x265/show_3efc8cc62864a33a3909f88efa50e937.jpg" />]]></description>                      
<stream_url><![CDATA[http://streamcloud.eu/ayyz8i8rkgge]]></stream_url>
 </channel>
 
 <channel>
 <title><![CDATA[8x10]]></title>
<logo_30x30><![CDATA[]]></logo_30x30>
<description><![CDATA[<img src="http://hdfull.tv/tthumb/172x265/show_3efc8cc62864a33a3909f88efa50e937.jpg" />]]></description>                      
<stream_url><![CDATA[http://streamcloud.eu/4md04m4izseo]]></stream_url>
 </channel>
 
  <channel>
 <title><![CDATA[8x11]]></title>
<logo_30x30><![CDATA[]]></logo_30x30>
<description><![CDATA[<img src="http://hdfull.tv/tthumb/172x265/show_3efc8cc62864a33a3909f88efa50e937.jpg" />]]></description>                      
<stream_url><![CDATA[http://streamcloud.eu/3olh8bq3ts0d]]></stream_url>
 </channel>
 
  <channel>
 <title><![CDATA[8x12]]></title>
<logo_30x30><![CDATA[]]></logo_30x30>
<description><![CDATA[<img src="http://hdfull.tv/tthumb/172x265/show_3efc8cc62864a33a3909f88efa50e937.jpg" />]]></description>                      
<stream_url><![CDATA[http://streamcloud.eu/0vmjyp83uw7t]]></stream_url>
 </channel>
 
  <channel>
 <title><![CDATA[8x13]]></title>
<logo_30x30><![CDATA[]]></logo_30x30>
<description><![CDATA[<img src="http://hdfull.tv/tthumb/172x265/show_3efc8cc62864a33a3909f88efa50e937.jpg" />]]></description>                      
<stream_url><![CDATA[http://streamcloud.eu/86m5jqythwij]]></stream_url>
 </channel>
 
  <channel>
 <title><![CDATA[8x14]]></title>
<logo_30x30><![CDATA[]]></logo_30x30>
<description><![CDATA[<img src="http://hdfull.tv/tthumb/172x265/show_3efc8cc62864a33a3909f88efa50e937.jpg" />]]></description>                      
<stream_url><![CDATA[http://streamcloud.eu/7ero9c25sbbt]]></stream_url>
 </channel>
 
  <channel>
 <title><![CDATA[8x15]]></title>
<logo_30x30><![CDATA[]]></logo_30x30>
<description><![CDATA[<img src="http://hdfull.tv/tthumb/172x265/show_3efc8cc62864a33a3909f88efa50e937.jpg" />]]></description>                      
<stream_url><![CDATA[http://streamcloud.eu/c8uiw7foptgt]]></stream_url>
 </channel>
 
  <channel>
 <title><![CDATA[8x16]]></title>
<logo_30x30><![CDATA[]]></logo_30x30>
<description><![CDATA[<img src="http://hdfull.tv/tthumb/172x265/show_3efc8cc62864a33a3909f88efa50e937.jpg" />]]></description>                      
<stream_url><![CDATA[http://streamcloud.eu/iy79dwwjt16z]]></stream_url>
 </channel>
 
  <channel>
 <title><![CDATA[8x17]]></title>
<logo_30x30><![CDATA[]]></logo_30x30>
<description><![CDATA[<img src="http://hdfull.tv/tthumb/172x265/show_3efc8cc62864a33a3909f88efa50e937.jpg" />]]></description>                      
<stream_url><![CDATA[http://streamcloud.eu/5770jm5qpmty]]></stream_url>
 </channel>
 
  <channel>
 <title><![CDATA[8x18]]></title>
<logo_30x30><![CDATA[]]></logo_30x30>
<description><![CDATA[<img src="http://hdfull.tv/tthumb/172x265/show_3efc8cc62864a33a3909f88efa50e937.jpg" />]]></description>                      
<stream_url><![CDATA[http://streamcloud.eu/qf1ol254smdq]]></stream_url>
 </channel>
 
  <channel>
 <title><![CDATA[9x01]]></title>
<logo_30x30><![CDATA[]]></logo_30x30>
<description><![CDATA[<img src="http://hdfull.tv/tthumb/172x265/show_3efc8cc62864a33a3909f88efa50e937.jpg" />]]></description>                      
<stream_url><![CDATA[http://streamcloud.eu/3vj08m4hrk5i]]></stream_url>
 </channel>
 
  <channel>
 <title><![CDATA[9x02]]></title>
<logo_30x30><![CDATA[]]></logo_30x30>
<description><![CDATA[<img src="http://hdfull.tv/tthumb/172x265/show_3efc8cc62864a33a3909f88efa50e937.jpg" />]]></description>                      
<stream_url><![CDATA[http://streamcloud.eu/pmz5ltamhyn7]]></stream_url>
 </channel>
 
  <channel>
 <title><![CDATA[9x03]]></title>
<logo_30x30><![CDATA[]]></logo_30x30>
<description><![CDATA[<img src="http://hdfull.tv/tthumb/172x265/show_3efc8cc62864a33a3909f88efa50e937.jpg" />]]></description>                      
<stream_url><![CDATA[http://streamcloud.eu/eaoj00wpvlrc]]></stream_url>
 </channel>
 
  <channel>
 <title><![CDATA[9x04]]></title>
<logo_30x30><![CDATA[]]></logo_30x30>
<description><![CDATA[<img src="http://hdfull.tv/tthumb/172x265/show_3efc8cc62864a33a3909f88efa50e937.jpg" />]]></description>                      
<stream_url><![CDATA[http://streamcloud.eu/42u6kzhnms2u]]></stream_url>
 </channel>
 
  <channel>
 <title><![CDATA[9x05]]></title>
<logo_30x30><![CDATA[]]></logo_30x30>
<description><![CDATA[<img src="http://hdfull.tv/tthumb/172x265/show_3efc8cc62864a33a3909f88efa50e937.jpg" />]]></description>                      
<stream_url><![CDATA[http://streamcloud.eu/iy0oxoobz8o8]]></stream_url>
 </channel>
 
  <channel>
 <title><![CDATA[9x06]]></title>
<logo_30x30><![CDATA[]]></logo_30x30>
<description><![CDATA[<img src="http://hdfull.tv/tthumb/172x265/show_3efc8cc62864a33a3909f88efa50e937.jpg" />]]></description>                      
<stream_url><![CDATA[http://streamcloud.eu/xy0zs1dizrzi]]></stream_url>
 </channel>
 
  <channel>
 <title><![CDATA[9x07]]></title>
<logo_30x30><![CDATA[]]></logo_30x30>
<description><![CDATA[<img src="http://hdfull.tv/tthumb/172x265/show_3efc8cc62864a33a3909f88efa50e937.jpg" />]]></description>                      
<stream_url><![CDATA[http://streamcloud.eu/6mdre0ag1vq4]]></stream_url>
 </channel>
 
  <channel>
 <title><![CDATA[9x08]]></title>
<logo_30x30><![CDATA[]]></logo_30x30>
<description><![CDATA[<img src="http://hdfull.tv/tthumb/172x265/show_3efc8cc62864a33a3909f88efa50e937.jpg" />]]></description>                      
<stream_url><![CDATA[http://streamcloud.eu/qybxnug1mb6k]]></stream_url>
 </channel>
 
  <channel>
 <title><![CDATA[9x09]]></title>
<logo_30x30><![CDATA[]]></logo_30x30>
<description><![CDATA[<img src="http://hdfull.tv/tthumb/172x265/show_3efc8cc62864a33a3909f88efa50e937.jpg" />]]></description>                      
<stream_url><![CDATA[http://streamcloud.eu/dgphgtu7tp2b]]></stream_url>
 </channel>
 
  <channel>
 <title><![CDATA[9x10]]></title>
<logo_30x30><![CDATA[]]></logo_30x30>
<description><![CDATA[<img src="http://hdfull.tv/tthumb/172x265/show_3efc8cc62864a33a3909f88efa50e937.jpg" />]]></description>                      
<stream_url><![CDATA[http://streamcloud.eu/enjzgz4d8dnu]]></stream_url>
 </channel>
 
   <channel>
 <title><![CDATA[9x11]]></title>
<logo_30x30><![CDATA[]]></logo_30x30>
<description><![CDATA[<img src="http://hdfull.tv/tthumb/172x265/show_3efc8cc62864a33a3909f88efa50e937.jpg" />]]></description>                      
<stream_url><![CDATA[http://streamcloud.eu/3x3zgv32fx0h]]></stream_url>
 </channel>
 
   <channel>
 <title><![CDATA[9x12]]></title>
<logo_30x30><![CDATA[]]></logo_30x30>
<description><![CDATA[<img src="http://hdfull.tv/tthumb/172x265/show_3efc8cc62864a33a3909f88efa50e937.jpg" />]]></description>                      
<stream_url><![CDATA[http://streamcloud.eu/2au8srvk9b94]]></stream_url>
 </channel>
 
   <channel>
 <title><![CDATA[9x13]]></title>
<logo_30x30><![CDATA[]]></logo_30x30>
<description><![CDATA[<img src="http://hdfull.tv/tthumb/172x265/show_3efc8cc62864a33a3909f88efa50e937.jpg" />]]></description>                      
<stream_url><![CDATA[http://streamcloud.eu/rh72b5kvcfd6]]></stream_url>
 </channel>
 
   <channel>
 <title><![CDATA[9x14]]></title>
<logo_30x30><![CDATA[]]></logo_30x30>
<description><![CDATA[<img src="http://hdfull.tv/tthumb/172x265/show_3efc8cc62864a33a3909f88efa50e937.jpg" />]]></description>                      
<stream_url><![CDATA[http://streamcloud.eu/cy6mk4ieuc3d]]></stream_url>
 </channel>
 
   <channel>
 <title><![CDATA[9x15]]></title>
<logo_30x30><![CDATA[]]></logo_30x30>
<description><![CDATA[<img src="http://hdfull.tv/tthumb/172x265/show_3efc8cc62864a33a3909f88efa50e937.jpg" />]]></description>                      
<stream_url><![CDATA[http://streamcloud.eu/3jd2lbob9sxf]]></stream_url>
 </channel>
 
   <channel>
 <title><![CDATA[9x16]]></title>
<logo_30x30><![CDATA[]]></logo_30x30>
<description><![CDATA[<img src="http://hdfull.tv/tthumb/172x265/show_3efc8cc62864a33a3909f88efa50e937.jpg" />]]></description>                      
<stream_url><![CDATA[http://streamcloud.eu/ekpko6qeppei]]></stream_url>
 </channel>
 
   <channel>
 <title><![CDATA[9x10]]></title>
<logo_30x30><![CDATA[]]></logo_30x30>
<description><![CDATA[<img src="http://hdfull.tv/tthumb/172x265/show_3efc8cc62864a33a3909f88efa50e937.jpg" />]]></description>                      
<stream_url><![CDATA[http://streamcloud.eu/2z5qcz0au3aj]]></stream_url>
 </channel>
 





 
 
 

 

  
  
  
  
  
  
<next_page_url text="CH+ FAVORITOS"><![CDATA[nStreamFavorites.xml]]></next_page_url>
<prev_page_url text="CH- ATRAS"><![CDATA[https://raw.githubusercontent.com/team1515/mirame/master/seriescompletas.xml]]></prev_page_url>
    </items>	
