<?xml version="1.0" encoding="iso-8859-1"?>
<items>
 <playlist_name>Fragiles >> T2</playlist_name>
  
 
<channel>
<title><![CDATA[El mendigo herido]]></title>
<logo_30x30><![CDATA[]]></logo_30x30>
<description><![CDATA[<img src="http://media2.mitele.es/uploads/2013/07/51ecfc5189021-660x371.jpg" />Pablo ya ejerce en su nueva consulta, situada en la casa de su amigo Mario, con el que comparte vivienda. Además, el fisioterapeuta cuenta con Lola, su antigua paciente y ahora amiga y recepcionista, que le ayudará a ordenar tanto su agenda laboral como su ajetreada vida personal.]]></description>
<stream_url><![CDATA[http://miteleooyala-vh.akamaihd.net/i/12OWxjNTE64hPJN-HNdq1ZPvfkxHbLqt/,DOcJ-FxaFrRg4gtDIwOjRpOmc3O3sK0o,DOcJ-FxaFrRg4gtDIwOjkzOjBhO6ZbhA,DOcJ-FxaFrRg4gtDIwOmY1OjBmO8qKJp,DOcJ-FxaFrRg4gtDIwOm84OjBmOyMgXz,DOcJ-FxaFrRg4gtDIwOjEwYjpnbTu6dZ,.csmil/index_4_av.m3u8?null=0]]></stream_url>
<buffer_kb>30000</buffer_kb>
</channel>
 
<channel>
<title><![CDATA[Las hermanas gimnastas]]></title>
<logo_30x30><![CDATA[]]></logo_30x30>
<description><![CDATA[<img src="http://media2.mitele.es/uploads/2013/07/51f64ff6b2776-660x371.jpg" />Pablo intenta mostrar indiferencia ante la recién estrenada relación de su compañero de piso y la que fue su amor, Teresa. Mientras, Ana, su exmujer, reaparece en su vida. Pablo, además, tendrá que tratar a Lena, ex gimnasta olímpica aquejada de una extraña parálisis en las piernas.]]></description>
<stream_url><![CDATA[http://miteleooyala-vh.akamaihd.net/i/Fsa2tjNTE65uBCU_Q8-MDK4eSZiuVdS9/,DOcJ-FxaFrRg4gtDMwOjRpOmc3O8NwzU,DOcJ-FxaFrRg4gtDMwOjkzOjBhO8a7FM,DOcJ-FxaFrRg4gtDMwOmY1OjBmO6dqUB,DOcJ-FxaFrRg4gtDMwOm84OjBmO7voI_,DOcJ-FxaFrRg4gtDMwOjEwYjpnbTte1w,.csmil/index_4_av.m3u8?null=0]]></stream_url>
<buffer_kb>30000</buffer_kb>
</channel>
 
<channel>
<title><![CDATA[El hombre irrompible]]></title>
<logo_30x30><![CDATA[]]></logo_30x30>
<description><![CDATA[<img src="http://media2.mitele.es/uploads/2013/08/51ffb4d271832-660x371.jpg" />Fredy (Raúl Prieto), acude a la consulta de Pablo porque tiene una lesión de codo tras un esfuerzo físico. Su mujer Miriam (Cristina Castaño), prima de Pablo, está muy preocupada por él porque desde hace un tiempo está obsesionado con levantar pesas. Tanto es así que su físico ha cambiado de una manera radical y teme que padezca vigorexia.]]></description>
<stream_url><![CDATA[http://miteleooyala-vh.akamaihd.net/i/B2c29jNTE6WoVPLd2lFZn1q-LlE7SqHI/,DOcJ-FxaFrRg4gtDIwOjRpOmc3O3sK0o,DOcJ-FxaFrRg4gtDIwOjkzOjBhO6ZbhA,DOcJ-FxaFrRg4gtDIwOmY1OjBmO8qKJp,DOcJ-FxaFrRg4gtDIwOm84OjBmOyMgXz,DOcJ-FxaFrRg4gtDIwOjEwYjpnbTu6dZ,.csmil/index_4_av.m3u8?null=0]]></stream_url>
<buffer_kb>30000</buffer_kb>
</channel>
 
<channel>
<title><![CDATA[Viejos amigos]]></title>
<logo_30x30><![CDATA[]]></logo_30x30>
<description><![CDATA[<img src="http://media2.mitele.es/uploads/2013/08/5208cccc44c85-660x371.jpg" />Lola está esperando un hijo y Jorge aunque ejercerá como padre de la criatura, el verdadero padre siempre será Nacho que reaparece inesperadamente en la vida de Lola. Además Teresa le contara a Mario lo que hubo entre ella y Pablo.]]></description>
<stream_url><![CDATA[http://miteleooyala-vh.akamaihd.net/i/NxNHZjNTE61CY7afNFbneHEHJog-E1jO/,DOcJ-FxaFrRg4gtDIwOjRpOmc3O3sK0o,DOcJ-FxaFrRg4gtDIwOjkzOjBhO6ZbhA,DOcJ-FxaFrRg4gtDIwOmY1OjBmO8qKJp,DOcJ-FxaFrRg4gtDIwOm84OjBmOyMgXz,DOcJ-FxaFrRg4gtDIwOjEwYjpnbTu6dZ,.csmil/index_4_av.m3u8?null=0]]></stream_url>
<buffer_kb>30000</buffer_kb>
</channel>
 
<channel>
<title><![CDATA[El deportista atropellado]]></title>
<logo_30x30><![CDATA[]]></logo_30x30>
<description><![CDATA[<img src="http://media2.mitele.es/uploads/2013/08/52147e73e52d1-660x371.jpg" />La magia que un día existió entre Pablo y Ana, su exmujer, irá resurgiendo poco a poco para desgracia de Teresa. En la consulta aparecerá Julián (Juanjo Artero) un hombre que ha sido atropellado por un conductor borracho.]]></description>
<stream_url><![CDATA[http://miteleooyala-vh.akamaihd.net/i/hkaHRjNTE62SUKTTNarQSqOzx5Jo8B-n/,DOcJ-FxaFrRg4gtDIwOjRpOmc3O3sK0o,DOcJ-FxaFrRg4gtDIwOjkzOjBhO6ZbhA,DOcJ-FxaFrRg4gtDIwOmY1OjBmO8qKJp,DOcJ-FxaFrRg4gtDIwOm84OjBmOyMgXz,DOcJ-FxaFrRg4gtDIwOjEwYjpnbTu6dZ,.csmil/index_4_av.m3u8?null=0]]></stream_url>
<buffer_kb>30000</buffer_kb>
</channel>
 
<channel>
<title><![CDATA[La monja milagrosa]]></title>
<logo_30x30><![CDATA[]]></logo_30x30>
<description><![CDATA[<img src="http://media2.mitele.es/uploads/2013/08/521b56c177655-660x371.jpg" />Ante su futura maternidad, Lola ve acrecentar sus dudas y temores. Y esas dudas parecen contagiar la vida sentimental de Pablo, que cada vez se cita más a menudo con una misteriosa mujer. Mientras, Sor Blanca (Malena Alterio), una joven monja, acude a la consulta de Pablo por tener los músculos excesivamente contracturados]]></description>
<stream_url><![CDATA[http://miteleooyala-vh.akamaihd.net/i/xmcHJjNTE6LWqb8131JeMDZFD4UvQb0R/,DOcJ-FxaFrRg4gtDMwOjRpOmc3O8NwzU,DOcJ-FxaFrRg4gtDMwOjkzOjBhO8a7FM,DOcJ-FxaFrRg4gtDMwOmY1OjBmO6dqUB,DOcJ-FxaFrRg4gtDMwOm84OjBmO7voI_,DOcJ-FxaFrRg4gtDMwOjEwYjpnbTte1w,.csmil/index_4_av.m3u8?null=0]]></stream_url>
<buffer_kb>30000</buffer_kb>
</channel>
 
<channel>
<title><![CDATA[El Extraterrestre]]></title>
<logo_30x30><![CDATA[]]></logo_30x30>
<description><![CDATA[<img src="http://media2.mitele.es/uploads/2013/09/5224573669b24-660x371.jpg" />Teresa, Ana, Inés y los problemas legales de Lola complican cada día más la ajetreada vida de Pablo, que recibe la inesperada visita de dos amigos de la juventud. Uno de ellos, Fabián (Antonio Molero), ha intentado suicidarse tras asegurar que es un extraterrestre]]></description>
<stream_url><![CDATA[http://miteleooyala-vh.akamaihd.net/i/1wY3NjNTE64c43d_YV219nPDOFYWQO2H/,DOcJ-FxaFrRg4gtDMwOjRpOmc3O8NwzU,DOcJ-FxaFrRg4gtDMwOjkzOjBhO8a7FM,DOcJ-FxaFrRg4gtDMwOmY1OjBmO6dqUB,DOcJ-FxaFrRg4gtDMwOm84OjBmO7voI_,DOcJ-FxaFrRg4gtDMwOjEwYjpnbTte1w,.csmil/index_4_av.m3u8?null=0]]></stream_url>
<buffer_kb>30000</buffer_kb>
</channel>
 
<channel>
<title><![CDATA[Sin miedo a nada]]></title>
<logo_30x30><![CDATA[]]></logo_30x30>
<description><![CDATA[<img src="http://media2.mitele.es/uploads/2013/09/522457758d8cb-660x371.jpg" />Mientras Lola está a punto de dar a luz, Mario deberá enfrentarse finalmente a su pasado. Pablo, por su parte, tendrá que afrontar sus propios miedos e inquietudes antes de tomar una decisión que cambiará su vida irremediablemente.]]></description>
<stream_url><![CDATA[http://miteleooyala-vh.akamaihd.net/i/BvbW5jNTE6jAJS1MpH2RCV3-YBvzaQiC/,DOcJ-FxaFrRg4gtDIwOjRpOmc3O3sK0o,DOcJ-FxaFrRg4gtDIwOjkzOjBhO6ZbhA,DOcJ-FxaFrRg4gtDIwOmY1OjBmO8qKJp,DOcJ-FxaFrRg4gtDIwOm84OjBmOyMgXz,DOcJ-FxaFrRg4gtDIwOjEwYjpnbTu6dZ,.csmil/index_4_av.m3u8?null=0]]></stream_url>
<buffer_kb>30000</buffer_kb>
</channel>
 
<next_page_url text="CH+ FAVORITOS"><![CDATA[nStreamFavorites.xml]]></next_page_url>
<prev_page_url text="CH- ATRAS"><![CDATA[https://raw.githubusercontent.com/team1515/mirame/master/seriescompletas.xml]]></prev_page_url>
 
</items>
