<?xml version="1.0" encoding="iso-8859-1"?>
<items>
 <playlist_name>LLeno por favor>> Temporada Completas</playlist_name>




 
<channel>
                        <title><![CDATA[1x01]]></title>
                        <logo_30x30><![CDATA[]]></logo_30x30>
                        <description><![CDATA[<img src="http://hdfull.tv/tthumb/172x265/show_7b88443d200c6ebed402d3fafeffd6f8.jpg" />]]></description>
                       <stream_url><![CDATA[http://streamcloud.eu/jf8p68hyy8en/Lleno_por_favor_1x01_Operacion_Salida__Dandy35_.avi.html]]></stream_url>
                           </channel>
 
 
 
<channel>
                        <title><![CDATA[1x02]]></title>
                        <logo_30x30><![CDATA[]]></logo_30x30>
                        <description><![CDATA[<img src="http://hdfull.tv/tthumb/172x265/show_7b88443d200c6ebed402d3fafeffd6f8.jpg" />]]></description>
                       <stream_url><![CDATA[http://streamcloud.eu/7gpf7elz24b8/0227_LlenoPorFavor_1x02_LiNkMaN.avi.html]]></stream_url>
                           </channel>
 
 
<channel>
                        <title><![CDATA[1x03]]></title>
                        <logo_30x30><![CDATA[]]></logo_30x30>
                        <description><![CDATA[<img src="http://hdfull.tv/tthumb/172x265/show_7b88443d200c6ebed402d3fafeffd6f8.jpg" />]]></description>
                       <stream_url><![CDATA[http://streamcloud.eu/nkxsf71562o7/0227_LlenoPorFavor_1x03_LiNkMaN.avi.html]]></stream_url>
                           </channel>
 
 
 
<channel>
                        <title><![CDATA[1x04]]></title>
                        <logo_30x30><![CDATA[]]></logo_30x30>
                        <description><![CDATA[<img src="http://hdfull.tv/tthumb/172x265/show_7b88443d200c6ebed402d3fafeffd6f8.jpg" />]]></description>
                       <stream_url><![CDATA[http://streamcloud.eu/qcwl17srnt6y/Lleno_por_favor-1x04.avi.html]]></stream_url>
                           </channel>
 
 
 
<channel>
                        <title><![CDATA[1x05]]></title>
                        <logo_30x30><![CDATA[]]></logo_30x30>
                        <description><![CDATA[<img src="http://hdfull.tv/tthumb/172x265/show_7b88443d200c6ebed402d3fafeffd6f8.jpg" />]]></description>
                       <stream_url><![CDATA[http://streamcloud.eu/t3a2ba1lx5ua/0227_LlenoPorFavor_1x05_LiNkMaN.avi.html]]></stream_url>
                           </channel>
 
 
 
<channel>
                        <title><![CDATA[1x06]]></title>
                        <logo_30x30><![CDATA[]]></logo_30x30>
                        <description><![CDATA[<img src="http://hdfull.tv/tthumb/172x265/show_7b88443d200c6ebed402d3fafeffd6f8.jpg" />]]></description>
                       <stream_url><![CDATA[http://streamcloud.eu/eqg522bjahec/Lleno_por_favor-1x06.avi.html]]></stream_url>
                           </channel>
 
 
<channel>
                        <title><![CDATA[1x07]]></title>
                        <logo_30x30><![CDATA[]]></logo_30x30>
                        <description><![CDATA[<img src="http://hdfull.tv/tthumb/172x265/show_7b88443d200c6ebed402d3fafeffd6f8.jpg" />]]></description>
                       <stream_url><![CDATA[http://streamcloud.eu/mvceesnud0sa/Lleno_por_favor_1x07_Rambo_Gil__Dandy35_.avi.html]]></stream_url>
                           </channel>
 
 
 
<channel>
                        <title><![CDATA[1x08]]></title>
                        <logo_30x30><![CDATA[]]></logo_30x30>
                        <description><![CDATA[<img src="http://hdfull.tv/tthumb/172x265/show_7b88443d200c6ebed402d3fafeffd6f8.jpg" />]]></description>
                       <stream_url><![CDATA[http://streamcloud.eu/gaw69jhd70cj/Lleno_Por_Favor_1x08_El_Vud____Dandy35_.avi.html]]></stream_url>
                           </channel>
 
 
<channel>
                        <title><![CDATA[1x09]]></title>
                        <logo_30x30><![CDATA[]]></logo_30x30>
                        <description><![CDATA[<img src="http://hdfull.tv/tthumb/172x265/show_7b88443d200c6ebed402d3fafeffd6f8.jpg" />]]></description>
                       <stream_url><![CDATA[http://streamcloud.eu/k35j7pr5neuc/Lleno_por_favor_1x09_Cine_Made_in_Spain__Dandy35_.avi.html]]></stream_url>
                           </channel>
 
 
 
<channel>
                        <title><![CDATA[1x10]]></title>
                        <logo_30x30><![CDATA[]]></logo_30x30>
                        <description><![CDATA[<img src="http://hdfull.tv/tthumb/172x265/show_7b88443d200c6ebed402d3fafeffd6f8.jpg" />]]></description>
                       <stream_url><![CDATA[http://streamcloud.eu/hn8xwvbdf5qm/Lleno_por_favor_1x10_Totus_tuus__Dandy35_.avi.html]]></stream_url>
                           </channel>
 
 
 
<channel>
                        <title><![CDATA[1x11]]></title>
                        <logo_30x30><![CDATA[]]></logo_30x30>
                        <description><![CDATA[<img src="http://hdfull.tv/tthumb/172x265/show_7b88443d200c6ebed402d3fafeffd6f8.jpg" />]]></description>
                       <stream_url><![CDATA[http://streamcloud.eu/6maepemdarvb/Lleno_por_favor_1x11_Aqui_Mando_Yo__Dandy35_.avi.html]]></stream_url>
                           </channel>
 
 
 
<channel>
                        <title><![CDATA[1x12]]></title>
                        <logo_30x30><![CDATA[]]></logo_30x30>
                        <description><![CDATA[<img src="http://hdfull.tv/tthumb/172x265/show_7b88443d200c6ebed402d3fafeffd6f8.jpg" />]]></description>
                       <stream_url><![CDATA[http://streamcloud.eu/p7iq6qkxcrxg/Lleno_por_favor_1x12_Quien_Sabe_donde___Dandy35_.avi.html]]></stream_url>
                           </channel>
 
 
<channel>
                        <title><![CDATA[1x13]]></title>
                        <logo_30x30><![CDATA[]]></logo_30x30>
                        <description><![CDATA[<img src="http://hdfull.tv/tthumb/172x265/show_7b88443d200c6ebed402d3fafeffd6f8.jpg" />]]></description>
                       <stream_url><![CDATA[http://streamcloud.eu/u617o893xezn/Lleno_por_favor_1x13_Y_que_cumplas_Muchos_mas__Dandy35_.avi.html]]></stream_url>
                           </channel>
						   
<next_page_url text="CH+ FAVORITOS"><![CDATA[nStreamFavorites.xml]]></next_page_url>
<prev_page_url text="CH- ATRAS"><![CDATA[https://raw.githubusercontent.com/team1515/mirame/master/seriescompletas.xml]]></prev_page_url>
    </items>						   
